ensdat/__init__.py
ensdat/defi.py
ensdat/destr.py
ensdat/o_chap.py
ensdat-0.0.2.dist-info/LICENSE
ensdat-0.0.2.dist-info/METADATA
ensdat-0.0.2.dist-info/WHEEL
ensdat-0.0.2.dist-info/top_level.txt
ensdat-0.0.2.dist-info/RECORD
