Metadata-Version: 2.1
Name: ensdat
Version: 0.0.2
Summary: encryption module
Home-page: https://github.com/Aqouthe
Author: Aqouthe
Author-email: hoonie0929@gmail.com
License: UNKNOWN
Platform: UNKNOWN
Classifier: Topic :: Security :: Cryptography
Classifier: Development Status :: 4 - Beta
Classifier: Programming Language :: Python :: 3
Classifier: License :: OSI Approved :: MIT License
Classifier: Operating System :: OS Independent
Requires-Python: >=3.6
License-File: LICENSE
Requires-Dist: os
Requires-Dist: cryptography
Requires-Dist: pycryptodome
Requires-Dist: pycryptodomex
